jupyter_requests/__init__.py
jupyter_requests/__version__.py
jupyter_requests/main.py
jupyter_requests-0.0.3.dist-info/METADATA
jupyter_requests-0.0.3.dist-info/RECORD
jupyter_requests-0.0.3.dist-info/WHEEL
jupyter_requests-0.0.3.dist-info/entry_points.txt
jupyter_requests-0.0.3.dist-info/top_level.txt
