Metadata-Version: 2.1
Name: jupyter-requests
Version: 0.0.3
Summary: Send requests to a Jupyter server.
Home-page: https://github.com/Zsailer/jupyter_requests
Author: Zach Sailer
Author-email: zachsailer@gmail.com
License: MIT
Platform: UNKNOWN
Classifier: License :: OSI Approved :: MIT License
Classifier: Programming Language :: Python
Classifier: Programming Language :: Python :: 3
Classifier: Programming Language :: Python :: 3.6
Classifier: Programming Language :: Python :: Implementation :: CPython
Classifier: Programming Language :: Python :: Implementation :: PyPy
Requires-Python: >=3.6.0
Requires-Dist: requests
